{
  "content": "炉炭烧人百疾生，凤狂龙躁减心情。四山毒瘴乾坤浊， \n一簟凉风世界清。楚调忽惊凄玉柱，汉宫应已湿金茎。 \n豪强顿息蛙唇吻，爽利重新鹘眼睛。稳想海槎朝犯斗， \n健思胡马夜翻营。东南亦是中华分，蒸郁相凌太不平。",
  "dynasty": "唐代",
  "id": 37172,
  "name": "喜凉",
  "poet": {
    "desc": "韩偓（公元842年～公元923年）。中国唐代诗人。乳名冬郎，字致光，号致尧，晚年又号玉山樵人。陕西万年县（今樊川）人。自幼聪明好学，10岁时，曾即席赋诗送其姨夫李商隐，令满座皆惊，李商隐称赞其诗是“雏凤清于老凤声”。龙纪元年(889年)，韩偓中进士，初在河中镇节度使幕府任职，后入朝历任左拾遗、左谏议大夫、度支副使、翰林学士。",
    "id": 130,
    "image": "https://raw.githubusercontent.com/hujiaweibujidao/poetry/master/image/image_130.jpg",
    "name": "韩偓",
    "star": 0
  },
  "star": 1,
  "tags": []
}