{
  "id": 63392,
  "star": 1,
  "name": "百字令（寿陈静山，少吾一岁）",
  "dynasty": "宋代",
  "content": "洞房停烛，似新岁，数到上元时节。一盏屠苏千岁酒，添得新人罗列。昨日迎长，今朝献寿，赏团团佳月。永和春好，用之不竭嘉客闻其新造酒永和镇百石。 <br> 见说海上归来，有如瓜大枣，无人分得。六十二三刘梦得，输与香山乐色。菱谷二绡，杨枝春草，歌舞琵琶笛。只愁元日，玉龙催上金驿。",
  "poet": {
    "id": 329,
    "star": 0,
    "name": "刘辰翁",
    "image": "http://img.gushiwen.org/authorImg/liuchenweng.jpg",
    "desc": "刘辰翁（1233.2.4—1297.2.12），字会孟，别号须溪。庐陵灌溪（今江西省吉安市吉安县梅塘乡小灌村）人。南宋末年著名的爱国诗人。 景定三年（1262）登进士第。他一生一生致力于文学创作和文学批评活动，为后人留下了可贵的丰厚文化遗产，遗著由子刘将孙编为《须溪先生全集》，《宋史·艺文志》著录为一百卷，已佚。"
  },
  "tags": []
}