{
  "id": 16162,
  "star": 1,
  "name": "泛舒城南溪赋得沙…张侍御赴河南元博士赴扬州拜觐仆射",
  "dynasty": "唐代",
  "content": "终日闾阎逐群鸡，喜逢野鹤临清溪。绿苔春水水中影， <br> 夜月平沙沙上栖。惊谓汀洲白蘋发，又疑曲渚前年雪。 <br> 紫顶昂藏肯狎人，一声嘹亮冲天阙。素质翩翩带落晖， <br> 湖南渭阳相背飞。东西分散别离促，宇宙苍茫相见稀。 <br> 皇华地仙如鹤驭，乘驾飘飘留不住。延望乘虚入紫霞， <br> 陌头回首空烟树。会使抟风羽翮轻，九霄云路随先鸣。",
  "poet": {
    "id": 745,
    "star": 0,
    "name": "刘商",
    "desc": "刘商，唐代诗人、画家，字子夏，彭城（今江苏徐州）人。大历（七六六至七七九）间进士。官礼部郎中。能文善画，诗以乐府见长。刘商的诗歌作品很多，代表作有《琴曲歌辞·胡笳十八拍》，这是他罢庐州合肥县令后所作，约写于大历四五年（769——770）。《唐才子传》卷四说他“拟蔡淡《胡笳曲》，脍炙当时”。《全唐诗》收录有刘商的很多诗歌。"
  },
  "tags": []
}