{
  "id": 72990,
  "star": 1,
  "name": "大风",
  "dynasty": "宋代",
  "content": "夜风昼不止，天理何可常。<br>正当春木荣，摆磨枝叶伤。<br>东皇务长养，乃值此物狂。<br>曷不诉於帝，斥之出远方。<br>风伯有罪五，孰肯进皂囊。<br>往时岁苦旱，救热雨欲滂。<br>吹之不使下，云雷遂深藏。<br>复摇江海波，白日沈舟航。<br>又卷关塞沙，千里填河隍。<br>拔木与退鷁，书传言已详。<br>今者天柔和，煦煦皆敷芳。<br>独尔何不仁，嚎怒事雄强。<br>既其背天时，诛殛固所当。<br>鸢鸣兼虎啸，助恶党亦昌。",
  "poet": {
    "id": 131,
    "star": 0,
    "name": "梅尧臣",
    "image": "http://img.gushiwen.org/authorImg/meiyaochen.jpg",
    "desc": "梅尧臣（1002～1060）字圣俞，世称宛陵先生，北宋著名现实主义诗人。汉族，宣州宣城（今属安徽）人。宣城古称宛陵，世称宛陵先生。初试不第，以荫补河南主簿。50岁后，于皇祐三年（1051）始得宋仁宗召试，赐同进士出身，为太常博士。以欧阳修荐，为国子监直讲，累迁尚书都官员外郎，故世称“梅直讲”、“梅都官”。曾参与编撰《新唐书》，并为《孙子兵法》作注，所注为孙子十家著（或十一家著）之一。有《宛陵先生集》60卷，有《四部丛刊》影明刊本等。词存二首。"
  },
  "tags": []
}