{
  "id": 30856,
  "star": 1,
  "name": "夏杪登越王楼临涪江望雪山寄朝中知友",
  "dynasty": "唐代",
  "content": "巴西西北楼，堪望亦堪愁。山乱江回远，川清树欲秋。 <br> 晴明中雪岭，烟霭下渔舟。写寄朝天客，知余恨独游。",
  "poet": {
    "id": 2288,
    "star": 0,
    "name": "于兴宗",
    "desc": "于兴宗，生卒年不详，唐京兆高陵（今陕西省三原县境内）人，于志宁侄子。（一说河南洛阳人）敬宗宝历二年(826)为东阳县令，宣宗大中七年(853)前后，以御史中丞守绵州刺史，后转洋州刺史，累官至河南少尹。兴宗能诗，与当时诗人如刘禹锡、方干、李朋、李汶儒等人均有交往酬和。其为绵州刺史时，曾登越王楼赋诗寄朝中诸友，一时文士如李朋、杨牢、薛蒙、李邺等十余人皆有和作。事迹散见刘禹锡《答东阳令寒碧图诗并引》、《新唐书·宰相世系表二下》、《唐诗纪事》卷五三。《全唐诗》存诗2首。其中《东阳涵碧亭》一诗，实乃方干《涵碧亭》诗之前四句。"
  },
  "tags": []
}