{
  "id": 70577,
  "star": 1,
  "name": "【越调】柳营曲_西山即事挽",
  "dynasty": "元代",
  "content": "西山即事<br>挽薛萝，倚嗟峨，人生胜游能几何？翠辇经过，彩笔吟哦，御墨尚岩阿。绿槐梦已南柯，苍松老似东坡。泉来山虎跑，花笑野猿歌。为甚么，僧寺占云多？<br>湖上<br>歌念奴，和昂夫，两风画船同笑语。水竹幽居，金碧浮图，倒影浸冰壶。山翁醉插茱萸，仙姬笑拈芙蕖。舞阑双鹧鸪，饮尽一葫芦。都，分韵赋的湖。<br>湖上晚兴<br>老画师，早春时，写松边一双白鹭鸶。拈断吟髭，点缀新词，渔舍小茅茨。寒香带雪南枝，晚妆临水西施。破苍苔斑竹枝，载红粉画船儿。诗．题满水仙词。<br>歌者玉卿<br>压锦丛，侍金童，蕊珠仙暂来尘世中。笋指纤秾，花貌春红，瑶台上记相逢。风清环珮丁东，月明仙掌芙蓉。琴横秋水冷，钗坠晓云松。天宝宫，惊走薛琼琼。<br>投闲即事<br>石斗滩，剑门关，上青天不如行路难。世事循环，春色阑珊，人老且投闲。文寻古调休弹，疏翁樵唱新刊。梅亭十二阑，茅屋两三间。看，一带好江山。<br>自会稽迁三衢三首<br>叠锦笺，卷青毡，行藏去住皆信天。梦笔名贤，载酒谪仙，相劝苦留连。守岩扉洞口白猿，伴渔蓑花下红鸳。拜辞了刘宠钱，笑上子猷船。迁，风月洁无边。高卧轩，赐荣园，风流晋唐人物贤。高会山川，秦望风烟，翠冷雨余天。镜湖上骑马乘船，翠微中急管繁弦。浣纱中争艳冶，采莲女斗蝉娟。还，此景有谁传？<br>诗酒缘，醒吟编，若耶山父老相爱怜。贺鉴湖边，夏后祠前，容我盖三椽。桃花流水神仙，竹篱茅舍林泉。五十亩种秫田，三两只钓鱼船。迁，移入小挑源。<br>包山书事<br>倚翠微，俯清溪，青山万里猿夜啼。怪我来迟，拂雪而归，月冷翠萝衣。啸白猿如醉如痴，远红尘无是无非。吟几篇绝句诗，看一局柯烂棋。饥，不采首阳薇。<br>酒边有诉秀才负心为作问答<br>望妾身，改家门，见书生可人情意亲。梦撒幺分，受尽艰辛，撅丁骂卜儿嗔。闪煞人也短命郎君，盼煞我也遥受夫人。皱双眉淡翠蛾，宽四指褪罗裙。又一春，花老月黄昏。<br>又答<br>秀才贫，记相亲，题花彩笺涂醉粉。念我白身，误却青春，千里践红尘。寄将来锦字口文，看承做梦岫行云。便金榜上标了贱名，丝鞭下就了新婚，包甚么限，包也还你做二夫人。",
  "poet": {
    "id": 394,
    "star": 0,
    "name": "张可久",
    "image": "http://img.gushiwen.org/authorImg/zhangkejiu.jpg",
    "desc": "张可久（约1270～1348以后）字小山（一说名伯远，字可久，号小山）（《尧山堂外纪》）；一说名张可久肖像（林晋生作）可久，字伯远，号小山（《词综》）；又一说字仲远，号小山（《四库全书总目提要》），庆元（治所在今浙江宁波鄞县）人，元朝重要散曲家，剧作家，与乔吉并称“双壁”，与张养浩合为“二张”。"
  },
  "tags": []
}