{
  "id": 23345,
  "star": 2,
  "name": "老热",
  "dynasty": "唐代",
  "content": "一饱百情足，一酣万事休。何人不衰老，我老心无忧。 <br> 仕者拘职役，农者劳田畴。何人不苦热，我热身自由。 <br> 卧风北窗下，坐月南池头。脑凉脱乌帽，足热濯清流。 <br> 慵发昼高枕，兴来夜泛舟。何乃有馀适，只缘无过求。 <br> 或问诸亲友，乐天是与不。亦无别言语，多道天悠悠。 <br> 悠悠君不知，此味深且幽。但恐君知后，亦来从我游。",
  "poet": {
    "id": 665,
    "star": 0,
    "name": "白居易",
    "image": "http://img.gushiwen.org/authorImg/baijuyi.jpg",
    "desc": "白居易（772年－846年），字乐天，号香山居士，又号醉吟先生，祖籍太原，到其曾祖父时迁居下邽，生于河南新郑。是唐代伟大的现实主义诗人，唐代三大诗人之一。白居易与元稹共同倡导新乐府运动，世称“元白”，与刘禹锡并称“刘白”。白居易的诗歌题材广泛，形式多样，语言平易通俗，有“诗魔”和“诗王”之称。官至翰林学士、左赞善大夫。公元846年，白居易在洛阳逝世，葬于香山。有《白氏长庆集》传世，代表诗作有《长恨歌》、《卖炭翁》、《琵琶行》等。"
  },
  "tags": []
}