{
  "id": 70467,
  "star": 1,
  "name": "【双调】新水令",
  "dynasty": "元代",
  "content": "彩云声断紫鸾箫，夜深沉绣帏中冷落。愁转增，不相饶。粉悴烟憔，云鬓乱倦梳掠。<br>【乔牌儿】自从他去了，无一日不口店道。眼皮儿不住了梭梭跳，料应他作念着。<br>【雁儿落】愁闻砧杵敲，倦听宾鸿叫。懒将烟粉施，羞对菱花照。<br>【挂玉钩】这些时针线慵拈懒绣作，愁闷的人颠倒。想着燕尔新婚那一宵，怎下得把奴抛调。意似痴，肌如削。只望他步步相随，谁承望拆散鸾交！<br>【乱柳叶】为他、为他曾把香烧，怎下的将咱、将咱抛调。惨可可曾对神明道，也不索，和他、和他叫。紧交，誓约，天开眼自然报。<br>【太平令】骂你个短命簿情才料，小可的无福怎生难消。想着咱月下星前期约，受了些无打算凄凉烦恼。我呵，你想着，记着，梦着，又被这雨打纱窗惊觉。<br>【豆叶黄】不觉的地北天南，抵多少水远山遥。一个粉脸儿，他身上何曾忘却。钟送黄昏鸡报晓，昏晓相催，断送了愁人，多多少少。<br>【七兄弟】懊恼，这宵，受煎熬，被凄凉一弄儿相刮躁。画檐间铁马儿晚风敲，纱窗外促织儿频频叫。<br>【梅花酒】孤帏儿静悄悄，烛灭烟消，枕剩衾薄。扑簌簌泪点抛，急煎煎眼难交。睡不着，更那堪雨潇潇！<br>【收江南】淅零零和泪上芭蕉，孤眠独枕最难熬。绛绡裙褪小蛮腰，急煎煎瘦了，相思满腹对谁学？<br>【尾】急煎煎每夜伤怀抱，扑簌簌泪点腮边落。唱道是废寝忘飧，玉减香消。小院深沉，孤帏里静悄。瘦影儿紧相随，一盏孤灯照。好教我急煎煎心痒难揉，则教我几声长吁到的晓。",
  "poet": {
    "id": 2697,
    "star": 0,
    "name": "商衟",
    "image": "http://img.gushiwen.org/authorImg/shangdao.jpg",
    "desc": "商衟，字正叔，一作政叔。曹州济阴（今山东曹县）人。出身于簪缨世家。先祖本姓殷，因避宋宣帝赵弘殷讳，改姓商。父锡，因正叔兄仕金显贵，封朝大夫。与元好问有通家之好，交谊颇厚。好问有《陇山行役图》诗二首，记正叔漂泊生涯及二人友谊，中有“陇坂经行十遇春”之句，说明他往来东西，客居秦陇之地甚久。好问《曹南商氏千秋录》又说他“滑稽豪侠，有古人风”。正叔好词曲，善绘画，曾改编南宋初年艺人张五牛所作《双渐小卿诸宫调》，为青楼名妓赵真真、杨玉娥所传唱，今已不传。又曾为名妓张怡云绘\"怡云图\"。明·朱权《太和正音谱》评其词\"如朝霞散彩\"。"
  },
  "tags": []
}