{
  "id": 69281,
  "star": 16,
  "name": "山居杂咏",
  "dynasty": "清代",
  "content": "锋镝牢囚取次过，依然不废我弦歌。<br>死犹未肯输心去，贫亦岂能奈我何！<br>廿两棉花装破被，三根松木煮空锅。<br>一冬也是堂堂地，岂信人间胜著多。",
  "poet": {
    "id": 540,
    "star": 0,
    "name": "黄宗羲",
    "image": "http://img.gushiwen.org/authorImg/huangzongxi.jpg",
    "desc": "黄宗羲（1610年9月24日—1695年8月12日）明末清初经学家、史学家、思想家、地理学家、天文历算学家、教育家，东林七君子黄尊素长子，汉族，浙江绍兴府余姚县人。字太冲，一字德冰，号南雷，别号梨洲老人、梨洲山人、蓝水渔人、鱼澄洞主、双瀑院长、古藏室史臣等，学者称梨洲先生。黄宗羲学问极博，思想深邃，著作宏富，与顾炎武、王夫之并称明末清初三大思想家（或清初三大儒）；与弟黄宗炎、黄宗会号称浙东三黄；与顾炎武、方以智、王夫之、朱舜水并称为“明末清初五大家”，亦有“中国思想启蒙之父”之誉。"
  },
  "tags": [
    "抒怀",
    "乐观",
    "言志"
  ]
}