{
  "id": 5689,
  "star": 1,
  "name": "送李太守赴上洛",
  "dynasty": "唐代",
  "content": "商山包楚邓，积翠蔼沉沉。驿路飞泉洒，关门落照深。 <br> 野花开古戍，行客响空林。板屋春多雨，山城昼欲阴。 <br> 丹泉通虢略，白羽抵荆岑。若见西山爽，应知黄绮心。",
  "poet": {
    "id": 515,
    "star": 0,
    "name": "王维",
    "image": "http://img.gushiwen.org/authorImg/wangwei.jpg",
    "desc": "王维（701年－761年，一说699年—761年），字摩诘，汉族，河东蒲州（今山西运城）人，祖籍山西祁县，唐朝诗人，有“诗佛”之称。苏轼评价其：“味摩诘之诗，诗中有画；观摩诘之画，画中有诗。”开元九年（721年）中进士，任太乐丞。王维是盛唐诗人的代表，今存诗400余首，重要诗作有《相思》《山居秋暝》等。王维精通佛学，受禅宗影响很大。佛教有一部《维摩诘经》，是王维名和字的由来。王维诗书画都很有名，非常多才多艺，音乐也很精通。与孟浩然合称“王孟”。"
  },
  "tags": []
}