{
  "id": 60988,
  "star": 1,
  "name": "满庭芳",
  "dynasty": "宋代",
  "content": "鼎用乾坤，药须乌兔，恁时方炼金丹。水中虎吼，火里赤龙蟠。兑是况铅震汞，自元谷、上至泥丸。些儿事，坎离复垢，返老作童颜。 <br> 五行，全四象，不调停火候，间断如闲。六天罡所指，玉出昆山。不动纤毫云雨，顷刻处、直透三关。黄庭内，一阳来复，丹就片时间。",
  "poet": {
    "id": 410,
    "star": 0,
    "name": "葛长庚",
    "image": "http://img.gushiwen.org/authorImg/gechanggeng.jpg",
    "desc": "白玉蟾(公元1194 - ?；现学界对其卒年尚有多种说法；)本姓葛，名长庚。为白氏继子，故又名白玉蟾。字如晦、紫清、白叟，号海琼子、海南翁、武夷散人、神霄散吏。南宋时人，祖籍福建闽清，生于琼州（今海南琼山）人，一说福建闽清人。幼聪慧，谙九经，能诗赋，长于书画，曾举童子科。及长，因“任侠杀人，亡命至武夷”。"
  },
  "tags": []
}