{
  "id": 69654,
  "star": 1,
  "name": "【双调】寿阳曲　四时",
  "dynasty": "元代",
  "content": "　　传心素，托简书，问春归欲归何处？送春词不题风共雨，止埋怨落花飞絮。<br>贪新酿，趁晚凉，笑相呼凭肩歌唱。最多情女郎心外想，打鸳鸯采莲湖上。萦心<br>事，惹恨词，更那堪动人秋思。画楼边几声新雁儿，不传书摆成个愁字。年华尽，<br>腊味醇，睡不温晓寒成阵。折梅花不传心上人，村煞我陇头春信。　咏所见<br>　　人如玉，鬓似云，动春心半含娇俊。近装奁懒将花貌匀，旋窝儿粉香成晕。　酒散<br>　　旗亭散，歌韵歇，暖风轻柳摇台榭。杏花墙夕阳春去也，马蹄香宝鞍敲月。　效香奁体<br>　　惚蝉鬓，怯镜鸾，雁声寒不禁肠断。碧纱窗夜长鸳梦短，怕黄昏一灯相伴。",
  "poet": {
    "id": 8,
    "star": 0,
    "name": "吴西逸",
    "desc": "[元]（约公元一三二〇年前后在世）名、里、生卒年均不详，约元仁宗延祐末前后在世。其散曲《自况》云：“万倾烟霞归路，一川花草香车，利名场上我情疏。蓝田堪种玉，鲁海可操觚，东风供睡足。”可从中窥见其性情。散曲内容多写自然景物、离愁别恨或个人的闲适生活，风格清丽疏淡。阿里西瑛作嬾云窝成，自题殿前欢，西逸及贯云石等均有和作。西逸所作曲，今存小令四十余支。（见太平乐府）太和正音谱评为“如空谷流泉。”"
  },
  "tags": []
}