{
  "id": 59809,
  "star": 1,
  "name": "水调歌头（圆史宰受荐）",
  "dynasty": "宋代",
  "content": "五剡乃脱选，通籍入金闺。祖宗立法初意，正欲猎英奇。近世流风薄矣，强者立跻霄汉，弱者困尘泥。流水伯牙操，底处有钟期。 <br> 公为政，民不扰，吏无欺。春风桃李满县，当路几人知。五马宏开公道，一鹗首旌治最，迟乃速之基。不枉受人荐，更看荐人时。",
  "poet": {
    "id": 2556,
    "star": 0,
    "name": "徐鹿卿",
    "image": "http://img.gushiwen.org/authorImg/xuluqing.jpg",
    "desc": "徐鹿卿（1170—1249），字德夫，号泉谷，隆兴丰城（今江西省丰城市白土镇后泉村）人。南宋文学家、藏书家。徐鹿卿生于宋孝宗乾道六年，卒于理宗淳祐九年，年八十岁。博通经史，以文学著名乡里。嘉定十六年，（公元一二二三年）廷试进士，调安南军学教授，复申理义之学。入为枢密院编修官。时刘克庄、王迈、方大琮皆因事被黜，他作诗赠之，并为弹劾。太学诸生作四贤诗美之。累官吏部侍郎，提举鸿禧观致仕。及卒，谥清正。鹿卿著有泉谷文集及奏议、讲议等，《宋史本传》传于世。"
  },
  "tags": []
}