{
  "id": 32556,
  "star": 1,
  "name": "下第寄知己",
  "dynasty": "唐代",
  "content": "长安孟春至，枯树花亦发。忧人此时心，冷若松上雪。 <br> 自知才不堪，岂敢频泣血。所痛无罪者，明时屡遭刖。 <br> 故山秋草多，一卷成古辙。夜来远心起，梦见潇湘月。 <br> 大贤冠盖高，何事怜屑屑。不令伤弓鸟，日暮飞向越。 <br> 闻知感激语，胸中如有物。举头望青天，白日头上没。 <br> 归来通济里，开户山鼠出。中庭广寂寥，但见薇与蕨。 <br> 无虑数尺躯，委作泉下骨。唯愁揽清镜，不见昨日发。 <br> 愿怜闺中女，晚嫁唯守节。勿惜四座言，女巧难自说。",
  "poet": {
    "id": 98,
    "star": 0,
    "name": "曹邺",
    "image": "http://img.gushiwen.org/authorImg/caoye.jpg",
    "desc": "曹邺，字邺之，桂州（桂林）阳朔人，与晚唐著名诗人刘驾、聂夷中、于濆、邵谒、苏拯齐名，而以曹邺才颖最佳。"
  },
  "tags": []
}