{
  "id": 10397,
  "star": 5,
  "name": "乐游园歌",
  "dynasty": "唐代",
  "content": "乐游古园崒森爽，烟绵碧草萋萋长。公子华筵势最高， <br> 秦川对酒平如掌。长生木瓢示真率，更调鞍马狂欢赏。 <br> 青春波浪芙蓉园，白日雷霆夹城仗。阊阖晴开昳荡荡， <br> 曲江翠幕排银榜。拂水低徊舞袖翻，缘云清切歌声上。 <br> 却忆年年人醉时，只今未醉已先悲。数茎白发那抛得， <br> 百罚深杯亦不辞。圣朝亦知贱士丑，一物自荷皇天慈。 <br> 此身饮罢无归处，独立苍茫自咏诗。",
  "poet": {
    "id": 474,
    "star": 0,
    "name": "杜甫",
    "image": "http://img.gushiwen.org/authorImg/dufu.jpg",
    "desc": "杜甫（712－770），字子美，自号少陵野老，世称“杜工部”、“杜少陵”等，汉族，河南府巩县（今河南省巩义市）人，唐代伟大的现实主义诗人，杜甫被世人尊为“诗圣”，其诗被称为“诗史”。杜甫与李白合称“李杜”，为了跟另外两位诗人李商隐与杜牧即“小李杜”区别开来，杜甫与李白又合称“大李杜”。他忧国忧民，人格高尚，他的约1400余首诗被保留了下来，诗艺精湛，在中国古典诗歌中备受推崇，影响深远。759-766年间曾居成都，后世有杜甫草堂纪念。"
  },
  "tags": []
}