{
  "id": 70538,
  "star": 1,
  "name": "【双调】江儿水",
  "dynasty": "元代",
  "content": "叹世<br>谁待理他闲是非，紧把红尘避。庵前绿水围，门外青山对，寻一个稳便处闲坐地。<br>竹冠草鞋粗布衣，晦迹韬光计。灰残风月心．参得烟霞味,寻一个稳便处闲坐地。<br>茅斋倚山门傍溪，镇日常关闭。安闲养此心，上住从吾意，寻一个稳便处闲坐地。<br>功名玉关十万里，委实劳心力。争如四皓仙，不愿三公位，寻一个稳便处闲坐地。<br>功劳既成名遂矣，便索抽身退。裴公绿野中，陶令东篱内，寻一个稳使处闲坐地。<br>笑他卧龙因甚起？不了终身计。贪甚青史名？弃却红尘利，寻一个稳使处闲坐地。<br>扁舟五湖越范蠡，有分烟波内。丝纶远是非，蓑笠多风味，寻一个稳便处闲坐地。<br>红尘不来侵钓矶，别却风云会。一钓了此生，七里全身计，寻一个稳便处闲坐地。<br>五柳绕庄菊满篱，自谓羲皇世。三径可信颜，一榻堪容膝，寻一个稳便处闲坐地。<br>妇人脸上笑靥<br>一团儿可人衠是娇，妆点如花貌。抬叠起脸上秋，出落腮边悄，千金这窠里消费了。",
  "poet": {
    "id": 1395,
    "star": 0,
    "name": "王仲元",
    "image": "http://img.gushiwen.org/authorImg/wangzhongyuan.jpg",
    "desc": "王仲元，元后期北曲作家，生平事迹不详。据《录鬼簿》载，他与钟嗣成相交有年，熟稔非常。王仲元其散曲多以杭州景致和西湖传说为题，表现了元末文采派曲家的风范。他还有两支以曲牌名连缀成套，状写情事和秋景的曲子，是元人散曲创作中的一种别致的“集专名”体的代表作，虽属文字游戏，但全套妥贴稳称，音律和谐，亦可卿备一格，是我们研究这类填曲技巧的范本。"
  },
  "tags": []
}