{
  "id": 56045,
  "star": 1,
  "name": "真珠帘",
  "dynasty": "宋代",
  "content": "山村水馆参差路。感＿游、正似残春风絮。掠地穿帘，知是竟归何处。镜里新霜空自悯，问几时、鸾台鳌署。迟暮。谩凭高怀远，书空独语。 <br> 自古。儒冠多误。悔当年、早不扁舟归去。醉下白苹洲，看夕阳鸥鹭。菰菜鲈鱼都弃了，只换得、青衫尘土。休顾。早收身江上，一蓑烟雨。",
  "poet": {
    "id": 272,
    "star": 0,
    "name": "陆游",
    "image": "http://img.gushiwen.org/authorImg/luyou.jpg",
    "desc": "陆游（1125—1210），字务观，号放翁。汉族，越州山阴（今浙江绍兴）人，南宋著名诗人。少时受家庭爱国思想熏陶，高宗时应礼部试，为秦桧所黜。孝宗时赐进士出身。中年入蜀，投身军旅生活，官至宝章阁待制。晚年退居家乡。创作诗歌今存九千多首，内容极为丰富。著有《剑南诗稿》、《渭南文集》、《南唐书》、《老学庵笔记》等。"
  },
  "tags": []
}