{
  "id": 64201,
  "star": 1,
  "name": "长亭怨（为任次山赋驯鹭）",
  "dynasty": "宋代",
  "content": "笑海上、白鸥盟冷。飞过前滩，又顾秋影。似我知鱼，乱蒲流水动清饮。岁华空老，犹一缕、柔丝恋顶。慵忆鸳行，想应是、朝回花径。 <br> 人静。怅离群日暮，都把野情消尽。山中旧隐。料独树、尚悬苍暝。引残梦、直上青天，又何处、溪风吹醒。定莫负、归舟同载，烟波千顷。",
  "poet": {
    "id": 53,
    "star": 0,
    "name": "张炎",
    "desc": "张炎（1248年－1320年），字叔夏，号玉田，晚年号乐笑翁。祖籍陕西凤翔。六世祖张俊，宋朝著名将领。父张枢，“西湖吟社”重要成员，妙解音律，与著名词人周密相交。张炎是勋贵之后，前半生居于临安，生活优裕，而宋亡以后则家道中落，晚年漂泊落拓。著有《山中白云词》，存词302首。张炎另一重要的贡献在于创作了中国最早的词论专著《词源》，总结整理了宋末雅词一派的主要艺术思想与成就，其中以“清空”，“骚雅”为主要主张。"
  },
  "tags": []
}