{
  "id": 3093,
  "star": 58,
  "name": "苑中遇雪应制",
  "dynasty": "唐代",
  "content": "紫禁仙舆诘旦来，青旂遥倚望春台。 <br>不知庭霰今朝落，疑是林花昨夜开。",
  "fanyi": "<p><strong>译文<br></strong>清晨的朝阳破云而出，就像皇家的銮驾从天边驶来。高楼上谁穿着青袍眺望，就像望春台边随风飘扬的青旗。<br>我不知道今天庭院中竟然落下了雪花，还以为是昨夜院中的树枝上开出的花。</p> <p><strong>注释<br></strong>①诘旦：平明﹐清晨。《宋书·柳元景传》：“自诘旦而战，至于日昃，虏众大溃。”<br>②旂：同“旗”。古代指有铃铛的旗子。</p>",
  "shangxi": "<h2>简析</h2> 　　不知道庭院里今朝落下了雪花（庭霰：指落在庭院里的雪花），还以为昨夜庭院枝上开了花，比喻生动、贴切",
  "poet": {
    "id": 248,
    "star": 0,
    "name": "宋之问",
    "image": "http://img.gushiwen.org/authorImg/songzhiwen.jpg",
    "desc": "宋之问，字延清，一名少连，汉族，汾州（今山西汾阳市）人。一说虢州弘农（今河南灵宝县）人。初唐时期的著名诗人。"
  },
  "tags": [
    "冬天",
    "写雪"
  ]
}