{
  "id": 8907,
  "star": 39,
  "name": "春思",
  "dynasty": "唐代",
  "content": "野花如雪绕江城，坐见年芳忆帝京。 <br>阊阖晓开凝碧树，曾陪鸳鹭听流莺。",
  "fanyi": "<h2>译文</h2> <pre id=\"best-content-1738201950\" class=\"best-text mb-10\" style=\"WORD-WRAP: break-word; MARGIN-BOTTOM: 10px; PADDING-BOTTOM: 0px; PADDING-TOP: 0px; PADDING-LEFT: 0px; MARGIN-TOP: 0px; PADDING-RIGHT: 0px\" accuse=\"aContent\"><span style=\"font-family:Arial, Verdana, sans-serif;\"><span style=\"WHITE-SPACE: normal\">野花如同雪花一样纷纷扬扬环绕江城，<br>犹看见一年一度的花草，回忆起来帝京，<br>早上宫门打开仿佛将碧绿的树都凝住了，<br>曾经陪鸳鹭听流莺得到叫声。</span></span></pre>",
  "poet": {
    "id": 564,
    "star": 0,
    "name": "韦应物",
    "image": "http://img.gushiwen.org/authorImg/weiyingwu.jpg",
    "desc": "韦应物（737～792），中国唐代诗人。汉族，长安(今陕西西安)人。今传有10卷本《韦江州集》、两卷本《韦苏州诗集》、10卷本《韦苏州集》。散文仅存一篇。因出任过苏州刺史，世称“韦苏州”。诗风恬淡高远，以善于写景和描写隐逸生活著称。"
  },
  "tags": [
    "春天",
    "怀念"
  ]
}